fodnet/__init__.py
fodnet/bin/__init__.py
fodnet/core/__init__.py
fodnet/core/dataset.py
fodnet/core/io.py
fodnet/core/model.py
fodnet/core/prediction.py
fodnet/core/processing.py
fodnet-1.1.0.dist-info/LICENSE
fodnet-1.1.0.dist-info/METADATA
fodnet-1.1.0.dist-info/WHEEL
fodnet-1.1.0.dist-info/top_level.txt
fodnet-1.1.0.dist-info/RECORD
