Metadata-Version: 2.1
Name: fodnet
Version: 1.1.0
Summary: FOD-Net Reimplementation.
Author: Matthew Lyon
Author-email: matthewlyon18@gmail.com
License: MIT License
Classifier: Programming Language :: Python
Classifier: Operating System :: Unix
Classifier: Operating System :: MacOS
Classifier: Operating System :: Microsoft :: Windows :: Windows 10
Requires-Python: >=3.8
License-File: LICENSE
Requires-Dist: torch >=2.0.0
Requires-Dist: lightning >=2.0.0
Requires-Dist: numpy
Requires-Dist: einops
Requires-Dist: scikit-image
Requires-Dist: nibabel
Requires-Dist: npy-patcher
